setup.cfg
setup.py
bin/zenhest
zenhest/__init__.py
zenhest.egg-info/PKG-INFO
zenhest.egg-info/SOURCES.txt
zenhest.egg-info/dependency_links.txt
zenhest.egg-info/requires.txt
zenhest.egg-info/top_level.txt