Metadata-Version: 1.1
Name: zenhest
Version: 0.0.6
Summary: Text based event console for Zenoss
Home-page: https://github.com/KimNorgaard/ZenHest
Author: Kim Nørgaard
Author-email: jasen@jasen.dk
License: MIT
Keywords: zenoss monitoring console
Platform: UNKNOWN
Classifier: Development Status :: 3 - Alpha
Classifier: Environment :: Console
Classifier: Intended Audience :: System Administrators
Classifier: License :: OSI Approved :: MIT License
Classifier: Natural Language :: English
Classifier: Operating System :: POSIX
Classifier: Programming Language :: Python :: 2.7
Classifier: Topic :: System :: Systems Administration
Classifier: Topic :: System :: Monitoring
Classifier: Topic :: Utilities
